{"name":"build-javascript","namedChunkGroups":{"polyfill":{"name":"polyfill","assets":[{"name":"webpack-runtime-f6fef6952141b7d80e56.js","size":4800},{"name":"polyfill-2ebf4ed6f68ba3299211.js","size":85045}],"filteredAssets":0,"assetsSize":89845,"filteredAuxiliaryAssets":2,"auxiliaryAssetsSize":229740},"app":{"name":"app","assets":[{"name":"webpack-runtime-f6fef6952141b7d80e56.js","size":4800},{"name":"framework-40ff62672ed89e0fca62.js","size":140753},{"name":"app-105b959b897b032a54b6.js","size":164579}],"filteredAssets":0,"assetsSize":310132,"filteredAuxiliaryAssets":3,"auxiliaryAssetsSize":1029339},"component---src-pages-404-tsx":{"name":"component---src-pages-404-tsx","assets":[{"name":"styles.c667350619746b283b11.css","size":17036},{"name":"a9a7754c-d4c9be9a497c8192983d.js","size":13797},{"name":"commons-db47230332fe2eb46a7c.js","size":90170},{"name":"component---src-pages-404-tsx-c3732097bdcfdc891b1f.js","size":910}],"filteredAssets":0,"assetsSize":121913,"filteredAuxiliaryAssets":3,"auxiliaryAssetsSize":792104},"component---src-pages-extra-tsx":{"name":"component---src-pages-extra-tsx","assets":[{"name":"styles.c667350619746b283b11.css","size":17036},{"name":"a9a7754c-d4c9be9a497c8192983d.js","size":13797},{"name":"commons-db47230332fe2eb46a7c.js","size":90170},{"name":"component---src-pages-extra-tsx-de822d27d610dff4b25c.js","size":18069}],"filteredAssets":0,"assetsSize":139072,"filteredAuxiliaryAssets":3,"auxiliaryAssetsSize":847085},"component---src-pages-index-tsx":{"name":"component---src-pages-index-tsx","assets":[{"name":"styles.c667350619746b283b11.css","size":17036},{"name":"a9a7754c-d4c9be9a497c8192983d.js","size":13797},{"name":"commons-db47230332fe2eb46a7c.js","size":90170},{"name":"component---src-pages-index-tsx-854e039ca7be9b302b1b.js","size":53999}],"filteredAssets":0,"assetsSize":175002,"filteredAuxiliaryAssets":3,"auxiliaryAssetsSize":986939}},"assetsByChunkName":{"polyfill":["webpack-runtime-f6fef6952141b7d80e56.js","polyfill-2ebf4ed6f68ba3299211.js"],"app":["webpack-runtime-f6fef6952141b7d80e56.js","framework-40ff62672ed89e0fca62.js","app-105b959b897b032a54b6.js"],"component---src-pages-404-tsx":["styles.c667350619746b283b11.css","a9a7754c-d4c9be9a497c8192983d.js","commons-db47230332fe2eb46a7c.js","component---src-pages-404-tsx-c3732097bdcfdc891b1f.js"],"component---src-pages-extra-tsx":["styles.c667350619746b283b11.css","a9a7754c-d4c9be9a497c8192983d.js","commons-db47230332fe2eb46a7c.js","component---src-pages-extra-tsx-de822d27d610dff4b25c.js"],"component---src-pages-index-tsx":["styles.c667350619746b283b11.css","a9a7754c-d4c9be9a497c8192983d.js","commons-db47230332fe2eb46a7c.js","component---src-pages-index-tsx-854e039ca7be9b302b1b.js"]},"childAssetsByChunkName":{}}